Metadata-Version: 2.1
Name: downloaderlib
Version: 2.5
Summary: This library is for downloading images, GitHub files, etc.
Home-page: UNKNOWN
Author-email: 0nameofshadow0@gmail.com
License: UNKNOWN
Platform: UNKNOWN
